CJiaochengCYuyanBianchengWang/README.md
CJiaochengCYuyanBianchengWang/__init__.py
CJiaochengCYuyanBianchengWang/__main__.py
CJiaochengCYuyanBianchengWang/file.epub
CJiaochengCYuyanBianchengWang/index.html
CJiaochengCYuyanBianchengWang/css/__init__.py
CJiaochengCYuyanBianchengWang/css/annotations.css
CJiaochengCYuyanBianchengWang/css/main.css
CJiaochengCYuyanBianchengWang/css/normalize.css
CJiaochengCYuyanBianchengWang/css/popup.css
CJiaochengCYuyanBianchengWang/font/__init__.py
CJiaochengCYuyanBianchengWang/font/fontello.eot
CJiaochengCYuyanBianchengWang/font/fontello.svg
CJiaochengCYuyanBianchengWang/font/fontello.ttf
CJiaochengCYuyanBianchengWang/font/fontello.woff
CJiaochengCYuyanBianchengWang/img/__init__.py
CJiaochengCYuyanBianchengWang/img/annotator-glyph-sprite.png
CJiaochengCYuyanBianchengWang/img/annotator-icon-sprite.png
CJiaochengCYuyanBianchengWang/img/apple-touch-icon.png
CJiaochengCYuyanBianchengWang/img/cancelfullscreen.png
CJiaochengCYuyanBianchengWang/img/close.png
CJiaochengCYuyanBianchengWang/img/fullscreen.png
CJiaochengCYuyanBianchengWang/img/loader.gif
CJiaochengCYuyanBianchengWang/img/menu-icon.png
CJiaochengCYuyanBianchengWang/img/save.png
CJiaochengCYuyanBianchengWang/img/saved.png
CJiaochengCYuyanBianchengWang/img/settings-s.png
CJiaochengCYuyanBianchengWang/img/settings.png
CJiaochengCYuyanBianchengWang/img/star.png
CJiaochengCYuyanBianchengWang/js/__init__.py
CJiaochengCYuyanBianchengWang/js/epub.js
CJiaochengCYuyanBianchengWang/js/epub.min.js
CJiaochengCYuyanBianchengWang/js/epub.min.map
CJiaochengCYuyanBianchengWang/js/hooks.min.js
CJiaochengCYuyanBianchengWang/js/hooks.min.map
CJiaochengCYuyanBianchengWang/js/reader.js
CJiaochengCYuyanBianchengWang/js/reader.js.map
CJiaochengCYuyanBianchengWang/js/reader.min.js
CJiaochengCYuyanBianchengWang/js/reader.min.map
CJiaochengCYuyanBianchengWang/js/hooks/__init__.py
CJiaochengCYuyanBianchengWang/js/hooks/extensions/__init__.py
CJiaochengCYuyanBianchengWang/js/hooks/extensions/highlight.js
c_jiaocheng_c_yuyan_biancheng_wang-2024.3.5.0.dist-info/METADATA
c_jiaocheng_c_yuyan_biancheng_wang-2024.3.5.0.dist-info/WHEEL
c_jiaocheng_c_yuyan_biancheng_wang-2024.3.5.0.dist-info/entry_points.txt
c_jiaocheng_c_yuyan_biancheng_wang-2024.3.5.0.dist-info/top_level.txt
c_jiaocheng_c_yuyan_biancheng_wang-2024.3.5.0.dist-info/RECORD
